LICENSE
README.rst
bash_completion.py
setup.py
bash_completion.egg-info/PKG-INFO
bash_completion.egg-info/SOURCES.txt
bash_completion.egg-info/dependency_links.txt
bash_completion.egg-info/not-zip-safe
bash_completion.egg-info/top_level.txt