Metadata-Version: 1.1
Name: bash-completion
Version: 0.1.0
Summary: Python interface for bash completion
Home-page: https://github.com/xonsh/py-bash-completion
Author: The xonsh developers
Author-email: xonsh@googlegroups.com
License: BSD 3-clause
Download-URL: https://github.com/xonsh/py-bash-completion/zipball/0.1.0
Platform: UNKNOWN
Classifier: License :: OSI Approved
Classifier: Intended Audience :: Developers
Classifier: Programming Language :: Python
Classifier: Topic :: Utilities
